cognite/processpool/__init__.py
cognite/processpool/processpool.py
cognite_processpool-0.7.0.dist-info/LICENSE
cognite_processpool-0.7.0.dist-info/WHEEL
cognite_processpool-0.7.0.dist-info/METADATA
cognite_processpool-0.7.0.dist-info/RECORD
