Metadata-Version: 2.1
Name: cognite-processpool
Version: 0.7.0
Summary: Stable process pool library
Author: Sander Land
Author-email: sander.land@cognite.com
Requires-Python: >=3.8,<4.0
Classifier: Programming Language :: Python :: 3
Classifier: Programming Language :: Python :: 3.8
Classifier: Programming Language :: Python :: 3.9
Classifier: Programming Language :: Python :: 3.10
Classifier: Programming Language :: Python :: 3.11
Requires-Dist: tblib (>=1.6.0,<2.0.0)
